{
  "model_generators": [
    {
      "find": "methods",
      "where": [
        {
          "constraint": "signature",
          "pattern": "Lcom/moblica/dmg/appsrv/ApplicationConnector;\\.sendAbstractGwMessage:.*"
        }
      ],
      "model": {
        "modes": [
          "skip-analysis"
        ]
      }
    },
    {
      "find": "methods",
      "where": [
        {
          "constraint": "signature",
          "pattern": "Lcom/moblica/utils/I(En|De)coder;\\.(en|de)code:.*"
        }
      ],
      "model": {
        "modes": [
          "skip-analysis",
          "no-join-virtual-overrides",
          "taint-in-taint-out",
          "taint-in-taint-this"
        ]
      }
    }
  ]
}
